cdeploy/__init__.py
cdeploy/cqlexecutor.py
cdeploy/exceptions.py
cdeploy/migrator.py
cdeploy/test/__init__.py
cdeploy/test/cqlexecutor_test.py
cdeploy/test/integration_test.py
cdeploy/test/migrator_test.py
cdeploy-1.7.dist-info/DESCRIPTION.rst
cdeploy-1.7.dist-info/METADATA
cdeploy-1.7.dist-info/RECORD
cdeploy-1.7.dist-info/WHEEL
cdeploy-1.7.dist-info/entry_points.txt
cdeploy-1.7.dist-info/metadata.json
cdeploy-1.7.dist-info/top_level.txt
